Metadata-Version: 2.1
Name: jk-pypiorgapi
Version: 0.2022.6.13
Summary: An API for accessing Python packet information hosted on pypi.org
Home-page: UNKNOWN
Author: Jürgen Knauth
Author-email: pubsrc@binary-overflow.de
License: Apache2
Keywords: pypi,pypi.org
Platform: UNKNOWN
Classifier: Development Status :: 4 - Beta
Classifier: License :: OSI Approved :: Apache Software License
Classifier: Programming Language :: Python :: 3
